rgb2gray/__init__.py
rgb2gray/_modidx.py
rgb2gray/converters.py
rgb2gray-0.0.4.dist-info/LICENSE
rgb2gray-0.0.4.dist-info/METADATA
rgb2gray-0.0.4.dist-info/WHEEL
rgb2gray-0.0.4.dist-info/entry_points.txt
rgb2gray-0.0.4.dist-info/top_level.txt
rgb2gray-0.0.4.dist-info/RECORD
