Metadata-Version: 2.1
Name: rgb2gray
Version: 0.0.4
Summary: rgb2gray
Home-page: https://github.com/camille1/rgb2gray/
Author: camille1
Author-email: 
License: Apache Software License 2.0
Keywords: nbdev
Classifier: Development Status :: 3 - Alpha
Classifier: Intended Audience :: Developers
Classifier: Natural Language :: English
Classifier: Programming Language :: Python :: 3.7
Classifier: Programming Language :: Python :: 3.8
Classifier: Programming Language :: Python :: 3.9
Classifier: Programming Language :: Python :: 3.10
Classifier: License :: OSI Approved :: Apache Software License
Requires-Python: >=3.7
License-File: LICENSE
Requires-Dist: numpy
Requires-Dist: pillow
Requires-Dist: matplotlib
Requires-Dist: opencv-python
Requires-Dist: requests
Provides-Extra: dev
